CHANGES.txt
LICENSE.txt
README.txt
koodaamo.pas.browseronlyredirect
setup.cfg
setup.py
koodaamo/__init__.py
koodaamo.pas.browseronlyredirect.egg-info/PKG-INFO
koodaamo.pas.browseronlyredirect.egg-info/SOURCES.txt
koodaamo.pas.browseronlyredirect.egg-info/dependency_links.txt
koodaamo.pas.browseronlyredirect.egg-info/entry_points.txt
koodaamo.pas.browseronlyredirect.egg-info/namespace_packages.txt
koodaamo.pas.browseronlyredirect.egg-info/not-zip-safe
koodaamo.pas.browseronlyredirect.egg-info/paster_plugins.txt
koodaamo.pas.browseronlyredirect.egg-info/requires.txt
koodaamo.pas.browseronlyredirect.egg-info/top_level.txt
koodaamo/pas/__init__.py
koodaamo/pas/browseronlyredirect/__init__.py
koodaamo/pas/browseronlyredirect/configure.zcml
koodaamo/pas/browseronlyredirect/install.py
koodaamo/pas/browseronlyredirect/plugin.py
koodaamo/pas/browseronlyredirect/browser/__init__.py
koodaamo/pas/browseronlyredirect/browser/add_plugin.zpt
koodaamo/pas/browseronlyredirect/browser/configure.zcml
koodaamo/pas/browseronlyredirect/browser/icon.gif