Metadata-Version: 1.1
Name: koodaamo.pas.browseronlyredirect
Version: 1.0
Summary: CookieAuthHelper to redirect only if user agent is a real browser
Home-page: http://github.com/koodaamo/koodaamo.pas.browseronlyredirect
Author: Petri Savolainen
Author-email: petri.savolainen@koodaamo.fi
License: GPL
Platform: UNKNOWN
Classifier: Framework :: Plone
Classifier: Intended Audience :: Developers
Classifier: License :: OSI Approved :: GNU General Public License (GPL)
